fluent_dashboard/__init__.py
fluent_dashboard/appgroups.py
fluent_dashboard/appsettings.py
fluent_dashboard/dashboard.py
fluent_dashboard/items.py
fluent_dashboard/menu.py
fluent_dashboard/modules.py
fluent_dashboard/locale/nl/LC_MESSAGES/django.mo
fluent_dashboard/locale/nl/LC_MESSAGES/django.po
fluent_dashboard/static/fluent_dashboard/dashboard.css
fluent_dashboard/static/fluent_dashboard/flaticons/archive52.png
fluent_dashboard/static/fluent_dashboard/flaticons/chat-1.png
fluent_dashboard/static/fluent_dashboard/flaticons/chat-2.png
fluent_dashboard/static/fluent_dashboard/flaticons/chat.png
fluent_dashboard/static/fluent_dashboard/flaticons/checklist4.png
fluent_dashboard/static/fluent_dashboard/flaticons/cogwheels9.png
fluent_dashboard/static/fluent_dashboard/flaticons/computermonitor17.png
fluent_dashboard/static/fluent_dashboard/flaticons/configure.png
fluent_dashboard/static/fluent_dashboard/flaticons/connectivity2.png
fluent_dashboard/static/fluent_dashboard/flaticons/document93.png
fluent_dashboard/static/fluent_dashboard/flaticons/documents56.png
fluent_dashboard/static/fluent_dashboard/flaticons/file.png
fluent_dashboard/static/fluent_dashboard/flaticons/global45.png
fluent_dashboard/static/fluent_dashboard/flaticons/globe16.png
fluent_dashboard/static/fluent_dashboard/flaticons/layout.png
fluent_dashboard/static/fluent_dashboard/flaticons/magnifier41.png
fluent_dashboard/static/fluent_dashboard/flaticons/main-page.png
fluent_dashboard/static/fluent_dashboard/flaticons/map35.png
fluent_dashboard/static/fluent_dashboard/flaticons/multiple25.png
fluent_dashboard/static/fluent_dashboard/flaticons/music236.png
fluent_dashboard/static/fluent_dashboard/flaticons/network60.png
fluent_dashboard/static/fluent_dashboard/flaticons/newspaper1.png
fluent_dashboard/static/fluent_dashboard/flaticons/notebook24.png
fluent_dashboard/static/fluent_dashboard/flaticons/notepad.png
fluent_dashboard/static/fluent_dashboard/flaticons/page15.png
django_fluent_dashboard-2.0.dist-info/AUTHORS
django_fluent_dashboard-2.0.dist-info/LICENSE
django_fluent_dashboard-2.0.dist-info/METADATA
django_fluent_dashboard-2.0.dist-info/WHEEL
django_fluent_dashboard-2.0.dist-info/top_level.txt
django_fluent_dashboard-2.0.dist-info/RECORD
